Metadata-Version: 2.4
Name: adafruit-circuitpython-husb238
Version: 1.0.6
Summary: CircuitPython helper library for the HUSB238 Type C Power Delivery Dummy Breakout
Author-email: Adafruit Industries <circuitpython@adafruit.com>
License: MIT
Project-URL: Homepage, https://github.com/adafruit/Adafruit_CircuitPython_HUSB238
Keywords: adafruit,blinka,circuitpython,micropython,husb238,usb,pd
Classifier: Intended Audience :: Developers
Classifier: Topic :: Software Development :: Libraries
Classifier: Topic :: Software Development :: Embedded Systems
Classifier: Topic :: System :: Hardware
Classifier: License :: OSI Approved :: MIT License
Classifier: Programming Language :: Python :: 3
License-File: LICENSE
Requires-Dist: Adafruit-Blinka
Requires-Dist: adafruit-circuitpython-busdevice
Requires-Dist: adafruit-circuitpython-register
Provides-Extra: optional
Dynamic: license-file
